rogue_sdk/__init__.py
rogue_sdk/client.py
rogue_sdk/sdk.py
rogue_sdk/types.py
rogue_sdk/websocket.py
rogue_sdk/tests/test_types.py
rogue_ai_sdk-0.3.4.dist-info/METADATA
rogue_ai_sdk-0.3.4.dist-info/WHEEL
rogue_ai_sdk-0.3.4.dist-info/licenses/LICENSE.md
rogue_ai_sdk-0.3.4.dist-info/RECORD
