Metadata-Version: 2.4
Name: rogue-ai-sdk
Version: 0.3.4
Summary: Python SDK for Rogue Agent Evaluator
Project-URL: Homepage, https://github.com/qualifire/rogue-agent-evaluator
Project-URL: Repository, https://github.com/qualifire/rogue-agent-evaluator
Project-URL: Issues, https://github.com/qualifire/rogue-agent-evaluator/issues
Author-email: Qualifire <support@qualifire.com>
License: Qualifire OSS License
License-File: LICENSE.md
Keywords: agent,evaluator,python,rogue,sdk
Classifier: Development Status :: 4 - Beta
Classifier: Intended Audience :: Developers
Classifier: License :: Free To Use But Restricted
Classifier: Programming Language :: Python :: 3
Classifier: Programming Language :: Python :: 3.9
Classifier: Programming Language :: Python :: 3.10
Classifier: Programming Language :: Python :: 3.11
Classifier: Programming Language :: Python :: 3.12
Classifier: Programming Language :: Python :: 3.13
Classifier: Topic :: Software Development :: Libraries :: Python Modules
Requires-Python: >=3.9
Requires-Dist: backoff>=2.2.1
Requires-Dist: httpx>=0.24.0
Requires-Dist: loguru>=0.7.0
Requires-Dist: pydantic>=2.0.0
Requires-Dist: typing-extensions>=4.0.0
Requires-Dist: websockets>=11.0.0
Provides-Extra: dev
Requires-Dist: black>=23.0.0; extra == 'dev'
Requires-Dist: flake8>=6.0.0; extra == 'dev'
Requires-Dist: isort>=5.0.0; extra == 'dev'
Requires-Dist: mypy>=1.0.0; extra == 'dev'
Requires-Dist: pytest-asyncio>=0.21.0; extra == 'dev'
Requires-Dist: pytest>=7.0.0; extra == 'dev'
